MIToolbox.cpython-310-x86_64-linux-gnu.so
FSToolbox.cpython-310-x86_64-linux-gnu.so
libFSToolbox.so
fstoolbox.libs/libMIToolbox-423b447f.so
fstoolbox-0.0.2.dist-info/METADATA
fstoolbox-0.0.2.dist-info/top_level.txt
fstoolbox-0.0.2.dist-info/RECORD
fstoolbox-0.0.2.dist-info/WHEEL
fstoolbox-0.0.2.dist-info/LICENSE
fstoolbox/__init__.py
fstoolbox/fstoolbox.py
MIToolbox/libMIToolbox.so
