Metadata-Version: 2.1
Name: fstoolbox
Version: 0.0.2
Summary: An information theoretic feature selection toolbox.
Home-page: https://github.com/Craigacp/FEAST
Author: Adam Pocock
Author-email: adam@adampocock.com
Maintainer: Brent Barbachem
Maintainer-email: barbacbd@gmail.com
License: MIT
Keywords: feast,feature,selection,fstoolbox
Classifier: Intended Audience :: Developers
Classifier: Intended Audience :: Education
Classifier: Intended Audience :: Other Audience
Classifier: Intended Audience :: Science/Research
Classifier: Natural Language :: English
Classifier: Programming Language :: Python :: 3
Classifier: Programming Language :: Python :: 3.9
Classifier: Programming Language :: Python :: 3.10
Classifier: Programming Language :: Python :: 3.11
Classifier: Topic :: Software Development
Requires-Python: >=3.9, <4
License-File: LICENSE
Requires-Dist: numpy
Requires-Dist: pandas
Requires-Dist: scikit-learn
